[
    {
        "id": "550e8400-e29b-41d4-a716-446655441201",
        "organization_id": "550e8400-e29b-41d4-a716-446655440001",
        "production_number": "PROD-25012701",
        "project_id": "550e8400-e29b-41d4-a716-446655440301",
        "status": "in_progress",
        "priority": "high",
        "planned_start_date": "2025-01-28T08:00:00.000Z",
        "planned_end_date": "2025-03-10T00:00:00.000Z",
        "actual_start_date": "2025-01-28T08:00:00.000Z",
        "actual_end_date": null,
        "quantity": 1000,
        "completed_quantity": 450,
        "assigned_to": "2de25409-78d3-4892-b4d3-9fbc252bc674",
        "notes": "Production order for Automotive Bracket Assembly project",
        "created_by": "6e8fc313-fd4b-4aa5-95b1-9021e2483d3a",
        "created_at": "2025-01-27T08:00:00.000Z",
        "updated_at": "2025-01-27T08:00:00.000Z"
    },
    {
        "id": "550e8400-e29b-41d4-a716-446655441202",
        "organization_id": "550e8400-e29b-41d4-a716-446655440001",
        "production_number": "PROD-25012702",
        "project_id": "550e8400-e29b-41d4-a716-446655440302",
        "status": "scheduled",
        "priority": "medium",
        "planned_start_date": "2025-02-01T08:00:00.000Z",
        "planned_end_date": "2025-02-25T00:00:00.000Z",
        "actual_start_date": null,
        "actual_end_date": null,
        "quantity": 500,
        "completed_quantity": 0,
        "assigned_to": "2de25409-78d3-4892-b4d3-9fbc252bc674",
        "notes": "Production order for Motorcycle Frame Welding project",
        "created_by": "6e8fc313-fd4b-4aa5-95b1-9021e2483d3a",
        "created_at": "2025-01-27T08:00:00.000Z",
        "updated_at": "2025-01-27T08:00:00.000Z"
    },
    {
        "id": "550e8400-e29b-41d4-a716-446655441203",
        "organization_id": "550e8400-e29b-41d4-a716-446655440001",
        "production_number": "PROD-25012703",
        "project_id": "550e8400-e29b-41d4-a716-446655440305",
        "status": "planned",
        "priority": "high",
        "planned_start_date": "2025-02-05T08:00:00.000Z",
        "planned_end_date": "2025-04-10T00:00:00.000Z",
        "actual_start_date": null,
        "actual_end_date": null,
        "quantity": 50,
        "completed_quantity": 0,
        "assigned_to": "2de25409-78d3-4892-b4d3-9fbc252bc674",
        "notes": "Production order for Industrial Control Panel project",
        "created_by": "6e8fc313-fd4b-4aa5-95b1-9021e2483d3a",
        "created_at": "2025-01-27T08:00:00.000Z",
        "updated_at": "2025-01-27T08:00:00.000Z"
    }
]